{
  "project_info": {
    "project_number": "145355602294",
    "project_id": "medic-link-prod",
    "storage_bucket": "medic-link-prod.appspot.com"
  },
  "client": [
    {
      "client_info": {
        "mobilesdk_app_id": "1:145355602294:android:b398176f8fd9a5703e2257",
        "android_client_info": {
          "package_name": "logbookorthouns2023.app.id"
        }
      },
      "oauth_client": [],
      "api_key": [
        {
          "current_key": "AIzaSyBKGHn9OOcdwB_C-bbFHKFxItsiOZYF9-Y"
        }
      ],
      "services": {
        "appinvite_service": {
          "other_platform_oauth_client": []
        }
      }
    }
  ],
  "configuration_version": "1"
}