{
  "id": "590189f4-80fe-4a36-acf7-eb9730c5d2f6",
  "name": "progress_bar",
  "content_tree": {
    "id": "yxxiwnsjlbs755r6m0b7nprf",
    "adv": {
      "css": "& {\n  display: flex;\n  width: 80%;\n\n  &:hover {\n    display: flex;\n  }\n}"
    },
    "name": "progress_bar",
    "type": "item",
    "childs": [
      {
        "id": "hmjtph6hax629gd3ckzdai74",
        "adv": {
          "css": "& {\n  display: flex;\n  \n  &:hover {\n    display: flex;\n  }\n}"
        },
        "name": "title_sec",
        "type": "item",
        "childs": [
          {
            "id": "mfdm42i9abcbb0lprc9w7tuq",
            "adv": {
              "js": "<div {...props}>\n{title}\n</div>",
              "css": "& {\n  display: flex;\n  font-weight: 500;\n  \n  &:hover {\n    display: flex;\n  }\n}",
              "jsBuilt": "render(React.createElement(\"div\",{...props},title));\n"
            },
            "dim": {
              "h": "fit",
              "w": "full"
            },
            "html": "Configuration Progress",
            "name": "title",
            "text": "",
            "type": "text",
            "childs": [],
            "layout": {
              "dir": "col",
              "gap": 0,
              "align": "center"
            },
            "mobile": {
              "dim": {
                "h": "fit",
                "w": "fit"
              },
              "font": {
                "size": 16,
                "color": "#002B5B",
                "family": "Poppins",
                "height": "auto"
              }
            },
            "component": {
              "props": {}
            }
          },
          {
            "id": "d1h5pef2rn0i8a5syhhu2yi6",
            "adv": {
              "js": "<>{button === \"visible\" && <div {...props} onClick={(e) => {\n  e.preventDefault()\n  window.location.href = button_url\n}}>{children}</div>}</>;",
              "jsBuilt": "render(React.createElement(React.Fragment,null,button===\"visible\"&&React.createElement(\"div\",{...props,onClick:e=>{e.preventDefault(),window.location.href=button_url}},children)));\n"
            },
            "name": "button_title",
            "type": "item",
            "childs": [
              {
                "id": "wg3mmnwd33iavcsfsx7ca6vi",
                "adv": {
                  "js": "<div {...props}>{children}</div>;\n",
                  "html": "<svg xmlns=\"http://www.w3.org/2000/svg\" width=\"24\" height=\"24\" fill=\"none\">\n<mask id=\"mask0_201_121\" style=\"mask-type:alpha\" maskUnits=\"userSpaceOnUse\" x=\"0\" y=\"0\" width=\"24\" height=\"24\">\n<rect width=\"24\" height=\"24\" fill=\"#D9D9D9\"/>\n</mask>\n<g mask=\"url(#mask0_201_121)\">\n<path d=\"M9.4 18L8 16.6L12.6 12L8 7.4L9.4 6L15.4 12L9.4 18Z\" fill=\"#1C1B1F\"/>\n</g>\n</svg>",
                  "jsBuilt": "render(React.createElement(\"div\",{...props},children));\n"
                },
                "dim": {
                  "h": "fit",
                  "w": "fit"
                },
                "name": "button",
                "type": "item",
                "childs": [],
                "component": {
                  "props": {}
                }
              }
            ],
            "component": {
              "props": {}
            }
          }
        ],
        "mobile": {
          "dim": {
            "h": "fit",
            "w": "full"
          },
          "layout": {
            "dir": "row",
            "gap": "auto",
            "align": "center"
          }
        },
        "component": {
          "props": {}
        }
      },
      {
        "id": "yk4nmakfrvgzsnzaqe3bdjz4",
        "adv": {
          "css": ""
        },
        "name": "progress_sec",
        "type": "item",
        "childs": [
          {
            "id": "s06hdxd3ph3ydkah5548exus",
            "adv": {
              "js": "<div {...props} style={{width: `${progress_percent}%`}}>\n{children}\n</div>",
              "jsBuilt": "render(React.createElement(\"div\",{...props,style:{width:`${progress_percent}%`}},children));\n"
            },
            "dim": {
              "h": "fit",
              "w": "fit"
            },
            "name": "progress",
            "type": "item",
            "childs": [],
            "mobile": {
              "bg": {
                "pos": "center",
                "size": "cover",
                "color": "#0062A3"
              },
              "dim": {
                "h": "full",
                "w": "fit"
              },
              "border": {
                "style": "solid",
                "rounded": {
                  "bl": 10,
                  "br": 10,
                  "tl": 10,
                  "tr": 10
                }
              }
            },
            "component": {
              "props": {}
            }
          }
        ],
        "mobile": {
          "bg": {
            "pos": "center",
            "size": "cover",
            "color": "#F2F2F2"
          },
          "dim": {
            "h": 30,
            "w": "full"
          },
          "border": {
            "style": "solid",
            "rounded": {
              "bl": 10,
              "br": 10,
              "tl": 10,
              "tr": 10
            }
          }
        },
        "component": {
          "props": {}
        }
      }
    ],
    "mobile": {
      "dim": {
        "h": "fit",
        "w": "full"
      },
      "layout": {
        "dir": "col",
        "gap": 10,
        "align": "center"
      }
    },
    "component": {
      "id": "590189f4-80fe-4a36-acf7-eb9730c5d2f6",
      "group": {
        "id": "e08f9ffa-e31f-4540-b651-a8b9ebd6e0e5",
        "name": "All"
      },
      "props": {
        "title": {
          "idx": 1,
          "meta": {
            "oldName": "new_prop"
          },
          "type": "string",
          "value": "\"hello\""
        },
        "button": {
          "idx": 2,
          "meta": {
            "type": "option",
            "oldName": "new_prop",
            "options": "[\n  { \n    label: \"hide\", \n    value: \"hide\" \n  },\n  { \n    label: \"visible\", \n    value: \"visible\" \n  },\n]"
          },
          "type": "string",
          "value": "\"visible\"",
          "valueBuilt": "\"visible\";\n"
        },
        "button_url": {
          "idx": 3,
          "meta": {
            "oldName": "new_prop"
          },
          "type": "string",
          "value": "\"/site/PPDS/main\"",
          "valueBuilt": "\"/site/PPDS/main\";\n"
        },
        "progress_percent": {
          "idx": 4,
          "meta": {
            "oldName": "new_prop"
          },
          "type": "string",
          "value": "\"0\"",
          "valueBuilt": "\"0\";\n"
        }
      }
    }
  },
  "created_at": "2023-07-28T05:14:46.649Z",
  "updated_at": "2023-08-09T03:56:14.247Z",
  "type": "item",
  "id_component_group": "e08f9ffa-e31f-4540-b651-a8b9ebd6e0e5",
  "props": []
}